remodel
tests
