Metadata-Version: 2.1
Name: remodel
Version: 1.0.0
Summary: RethinkDB ODM
Home-page: http://github.com/linkyndy/remodel
Author: Andrei Horak
Author-email: linkyndy@gmail.com
License: MIT
Platform: any
Classifier: Environment :: Web Environment
Classifier: Intended Audience :: Developers
Classifier: License :: OSI Approved :: MIT License
Classifier: Operating System :: OS Independent
Classifier: Programming Language :: Python
Classifier: Topic :: Internet :: WWW/HTTP :: Dynamic Content
Classifier: Topic :: Software Development :: Libraries :: Python Modules
Provides-Extra: dev
